{
    "nodes": [
        {
            "id": 0,
            "type": "robot",
            "attributes": {
                "color": "",
                "label": "",
                "position": [],
                "operation": [],
                "state": ""
            }
        },
        {
            "id": 1,
            "type": "large_object",
            "attributes": {
                "color": "yellow",
                "label": "box",
                "position": [],
                "operation": [
                    "place_to"
                ],
                "state": ""
            }
        },
        {
            "id": 2,
            "type": "small_object",
            "attributes": {
                "color": "orange",
                "label": "cantaloupe",
                "position": [],
                "operation": [
                    "pick"
                ],
                "state": ""
            }
        },
        {
            "id": 3,
            "type": "room",
            "attributes": {
                "color": "",
                "label": "bedroom",
                "position": [],
                "operation": [],
                "state": ""
            }
        }
    ],
    "edges": [
        {
            "id": 0,
            "type": "near",
            "source": 1,
            "target": 0,
            "attributes": {
                "label": ""
            }
        },
        {
            "id": 1,
            "type": "grasp",
            "source": 0,
            "target": 2,
            "attributes": {
                "label": ""
            }
        },
        {
            "id": 2,
            "type": "in",
            "source": 0,
            "target": 3,
            "attributes": {
                "label": ""
            }
        },
        {
            "id": 3,
            "type": "in",
            "source": 1,
            "target": 3,
            "attributes": {
                "label": ""
            }
        }
    ]
}